corphandouts/__init__.py
corphandouts/admin.py
corphandouts/apps.py
corphandouts/auth_hooks.py
corphandouts/corptools.py
corphandouts/models.py
corphandouts/multibuy.py
corphandouts/tasks.py
corphandouts/urls.py
corphandouts/views.py
corphandouts/locale/en/LC_MESSAGES/django.po
corphandouts/management/commands/corphandouts_check_all.py
corphandouts/migrations/0001_initial.py
corphandouts/migrations/__init__.py
corphandouts/templates/corphandouts/base.html
corphandouts/templates/corphandouts/doctrine.html
corphandouts/templates/corphandouts/fittings.html
corphandouts/templates/corphandouts/index.html
corphandouts/templates/corphandouts/modals/base.html
corphandouts/templates/corphandouts/modals/content_base.html
corphandouts/templates/corphandouts/modals/fit_corrections.html
corphandouts/templates/corphandouts/modals/generic_modal_page.html
corphandouts/templates/corphandouts/modals/loader_body.html
corphandouts/templates/corphandouts/partials/fit_corrections.html
corphandouts/templates/corphandouts/partials/handle_modals.html
corphandouts/templates/corphandouts/partials/nav_collapse_left.html
corphandouts/templatetags/__init__.py
corphandouts/templatetags/corphandouts.py
corphandouts/tests/__init__.py
corphandouts/tests/test_buyall.py
corphandouts/tests/test_corptools.py
corphandouts/tests/test_models.py
corphandouts/tests/test_tasks.py
corphandouts/tests/testdata/README.md
corphandouts/tests/testdata/__init__.py
corphandouts/tests/testdata/create_eveuniverse.py
corphandouts/tests/testdata/eveuniverse.json
corphandouts/tests/testdata/load_eveuniverse.py
corphandouts/tests/utils/__init__.py
corphandouts/tests/utils/corptools.py
corphandouts/tests/utils/fitting.py
aa_corphandouts-1.0.2.dist-info/licenses/LICENSE
aa_corphandouts-1.0.2.dist-info/WHEEL
aa_corphandouts-1.0.2.dist-info/METADATA
aa_corphandouts-1.0.2.dist-info/RECORD
