Metadata-Version: 2.4
Name: aa-corphandouts
Version: 1.0.2
Summary: Plugin to check the fitting of corporation handouts
Author-email: T'rahk Rokym <trahk.rokym@gmail.com>
Requires-Python: >=3.10
Classifier: Environment :: Web Environment
Classifier: Framework :: Django
Classifier: Framework :: Django :: 4.0
Classifier: Framework :: Django :: 4.2
Classifier: Intended Audience :: Developers
Classifier: License :: OSI Approved :: MIT License
Classifier: Operating System :: OS Independent
Classifier: Programming Language :: Python
Classifier: Programming Language :: Python :: 3.10
Classifier: Programming Language :: Python :: 3.11
Classifier: Programming Language :: Python :: 3.12
Classifier: Topic :: Internet :: WWW/HTTP
Classifier: Topic :: Internet :: WWW/HTTP :: Dynamic Content
License-File: LICENSE
Requires-Dist: allianceauth>=4
Requires-Dist: fittings>=2.1
Requires-Dist: allianceauth-corptools>=2.10.1
Project-URL: Changelog, https://gitlab.com/r0kym/aa-corphandouts/-/blob/master/CHANGELOG.md
Project-URL: Homepage, https://gitlab.com/r0kym/aa-corphandouts/
Project-URL: Source, https://gitlab.com/r0kym/aa-corphandouts/
Project-URL: Tracker, https://gitlab.com/r0kym/aa-corphandouts/-/issues
